model_measure/__init__.py
model_measure/main.py
model_measure-0.0.1.dist-info/METADATA
model_measure-0.0.1.dist-info/WHEEL
model_measure-0.0.1.dist-info/top_level.txt
model_measure-0.0.1.dist-info/RECORD
