Metadata-Version: 2.1
Name: model_measure
Version: 0.0.1
Summary: Machine learning model measurement
Author: Dhivya Nagasubramanian
Author-email: nagas021@alumni.umn.edu
Classifier: Programming Language :: Python :: 3
Classifier: License :: OSI Approved :: MIT License
Classifier: Operating System :: OS Independent
Requires-Python: >=3.6
